AUTHORS
LICENSE
MANIFEST.in
README.md
setup.py
py_opengauss/__init__.py
py_opengauss/alock.py
py_opengauss/api.py
py_opengauss/clientparameters.py
py_opengauss/cluster.py
py_opengauss/configfile.py
py_opengauss/copyman.py
py_opengauss/exceptions.py
py_opengauss/installation.py
py_opengauss/iri.py
py_opengauss/message.py
py_opengauss/notifyman.py
py_opengauss/pgpassfile.py
py_opengauss/project.py
py_opengauss/string.py
py_opengauss/sys.py
py_opengauss/temporal.py
py_opengauss/versionstring.py
py_opengauss.egg-info/PKG-INFO
py_opengauss.egg-info/SOURCES.txt
py_opengauss.egg-info/dependency_links.txt
py_opengauss.egg-info/top_level.txt
py_opengauss/bin/__init__.py
py_opengauss/bin/pg_dotconf.py
py_opengauss/bin/pg_python.py
py_opengauss/documentation/__init__.py
py_opengauss/documentation/sphinx/admin.rst
py_opengauss/documentation/sphinx/alock.rst
py_opengauss/documentation/sphinx/bin.rst
py_opengauss/documentation/sphinx/changes-v1.0.rst
py_opengauss/documentation/sphinx/changes-v1.1.rst
py_opengauss/documentation/sphinx/changes-v1.2.rst
py_opengauss/documentation/sphinx/changes-v1.3.rst
py_opengauss/documentation/sphinx/clientparameters.rst
py_opengauss/documentation/sphinx/cluster.rst
py_opengauss/documentation/sphinx/conf.py
py_opengauss/documentation/sphinx/copyman.rst
py_opengauss/documentation/sphinx/driver.rst
py_opengauss/documentation/sphinx/gotchas.rst
py_opengauss/documentation/sphinx/index.rst
py_opengauss/documentation/sphinx/lib.rst
py_opengauss/documentation/sphinx/notifyman.rst
py_opengauss/documentation/sphinx/reference.rst
py_opengauss/driver/__init__.py
py_opengauss/driver/dbapi20.py
py_opengauss/driver/pq3.py
py_opengauss/encodings/__init__.py
py_opengauss/encodings/aliases.py
py_opengauss/encodings/bytea.py
py_opengauss/lib/__init__.py
py_opengauss/lib/libsys.sql
py_opengauss/port/__init__.py
py_opengauss/port/signal1_msw.py
py_opengauss/port/_optimized/buffer.c
py_opengauss/port/_optimized/element3.c
py_opengauss/port/_optimized/functools.c
py_opengauss/port/_optimized/module.c
py_opengauss/port/_optimized/structlib.c
py_opengauss/port/_optimized/wirestate.c
