Metadata-Version: 2.1
Name: py-opengauss
Version: 1.3.10
Summary: Opengauss driver and tools library.
Home-page: https://gitee.com/opengauss/openGauss-connector-python-pyog
Author: James William Pye
Author-email: james.pye@gmail.com
Maintainer: Vimiix
Maintainer-email: i@vimiix.com
License: UNKNOWN
Platform: UNKNOWN
Classifier: Development Status :: 5 - Production/Stable
Classifier: Intended Audience :: Developers
Classifier: License :: OSI Approved :: BSD License
Classifier: License :: OSI Approved :: MIT License
Classifier: License :: OSI Approved :: Attribution Assurance License
Classifier: License :: OSI Approved :: Python Software Foundation License
Classifier: Natural Language :: English
Classifier: Operating System :: OS Independent
Classifier: Programming Language :: Python
Classifier: Programming Language :: Python :: 3
Classifier: Topic :: Database
Requires-Python: >=3.3
License-File: LICENSE
License-File: AUTHORS
